README.md
setup.py
tkml/__init__.py
tkml/_settings.py
tkml/helpers.py
tkml/info.ini
tkml/loader.py
tkml/locale.py
tkml.egg-info/PKG-INFO
tkml.egg-info/SOURCES.txt
tkml.egg-info/dependency_links.txt
tkml.egg-info/requires.txt
tkml.egg-info/top_level.txt