Metadata-Version: 1.1
Name: tkml
Version: 0.5
Summary: Tkinter gui representation
Home-page: https://bitbucket.org/cacilhas/tkml/
Author: ℜodrigo ℭacilhας
Author-email: batalema@cacilhas.info
License: UNKNOWN
Platform: UNKNOWN
Classifier: Environment :: X11 Applications
Classifier: License :: OSI Approved :: BSD License
Classifier: Programming Language :: Python :: 3.6
Classifier: Programming Language :: Python :: 3 :: Only
Classifier: Topic :: Software Development :: Libraries :: Python Modules
Provides: tkml
